loadneptun.py
loadneptun-0.3.dist-info/METADATA
loadneptun-0.3.dist-info/RECORD
loadneptun-0.3.dist-info/WHEEL
loadneptun-0.3.dist-info/top_level.txt
