Metadata-Version: 2.1
Name: loadneptun
Version: 0.3
Summary: loadneptun(versionNumber): returns a pandas dataframe with the neptun_db of the correct version
Home-page: UNKNOWN
Author: UNKNOWN
Author-email: UNKNOWN
License: UNKNOWN
Platform: UNKNOWN
